pyrepl/__init__.py
pyrepl/_minimal_curses.py
pyrepl/_version.py
pyrepl/cmdrepl.py
pyrepl/commands.py
pyrepl/completer.py
pyrepl/completing_reader.py
pyrepl/console.py
pyrepl/curses.py
pyrepl/fancy_termios.py
pyrepl/historical_reader.py
pyrepl/input.py
pyrepl/keymap.py
pyrepl/keymaps.py
pyrepl/module_lister.py
pyrepl/python_reader.py
pyrepl/pythoni.py
pyrepl/pythoni1.py
pyrepl/reader.py
pyrepl/readline.py
pyrepl/simple_interact.py
pyrepl/trace.py
pyrepl/unix_console.py
pyrepl/unix_eventqueue.py
pyrepl-0.11.3.post1.dist-info/licenses/LICENSE
pyrepl-0.11.3.post1.dist-info/METADATA
pyrepl-0.11.3.post1.dist-info/WHEEL
pyrepl-0.11.3.post1.dist-info/entry_points.txt
pyrepl-0.11.3.post1.dist-info/top_level.txt
pyrepl-0.11.3.post1.dist-info/RECORD
