Metadata-Version: 2.4
Name: pyrepl
Version: 0.11.3.post1
Summary: A library for building flexible command line interfaces
Author-email: Michael Hudson-Doyle <micahel@gmail.com>
Maintainer-email: bretello <bretello@distruzione.org>
License: MIT X11 style
Project-URL: homepage, https://github.com/bretello/pyrepl
Project-URL: issues, https://github.com/bretello/pyrepl/issues
Keywords: readline,shell
Classifier: Development Status :: 4 - Beta
Classifier: Environment :: Console
Classifier: License :: OSI Approved :: BSD License
Classifier: Programming Language :: Python :: 3.8
Classifier: Programming Language :: Python :: 3.9
Classifier: Programming Language :: Python :: 3.10
Classifier: Programming Language :: Python :: 3.11
Classifier: Programming Language :: Python :: 3.12
Classifier: Intended Audience :: Developers
Classifier: Operating System :: POSIX
Classifier: Operating System :: Microsoft :: Windows
Classifier: Topic :: Utilities
Requires-Python: >=3.8
License-File: LICENSE
Provides-Extra: tests
Requires-Dist: pytest; extra == "tests"
Requires-Dist: pytest-coverage; extra == "tests"
Requires-Dist: pytest-timeout; extra == "tests"
Requires-Dist: pexpect; extra == "tests"
Provides-Extra: dev
Requires-Dist: ruff==0.9.3; extra == "dev"
Requires-Dist: pyrepl[tests]; extra == "dev"
Dynamic: license-file
